django_kelove_setting/__init__.py
django_kelove_setting/admin.py
django_kelove_setting/apps.py
django_kelove_setting/kelove_settings.py
django_kelove_setting/migrations/0001_initial.py
django_kelove_setting/migrations/0002_alter_settings_id.py
django_kelove_setting/migrations/__init__.py
django_kelove_setting/models.py
django_kelove_setting/setting_forms.py
django_kelove_setting/templates/kelove_setting/change_form.html
django_kelove_setting/templates/kelove_setting/form_css.html
django_kelove_setting/utils.py
django_kelove_setting-2.0.5.dist-info/WHEEL
django_kelove_setting-2.0.5.dist-info/LICENSE
django_kelove_setting-2.0.5.dist-info/METADATA
django_kelove_setting-2.0.5.dist-info/RECORD
