Metadata-Version: 2.1
Name: django-kelove-setting
Version: 2.0.5
Summary: DJANGO 配置管理
Home-page: https://gitee.com/itxq/django-kelove-setting
License: Apache-2.0
Keywords: django,django-kelove,django-kelove-setting
Author: IT小强xqitw.cn
Author-email: mail@xqitw.cn
Maintainer: IT小强xqitw.cn
Maintainer-email: mail@xqitw.cn
Requires-Python: >=3.8,<4.0
Classifier: Development Status :: 3 - Alpha
Classifier: Framework :: Django :: 3.1
Classifier: Framework :: Django :: 3.2
Classifier: Framework :: Django :: 4.0
Classifier: Framework :: Django :: 4.1
Classifier: Intended Audience :: Developers
Classifier: License :: OSI Approved :: Apache Software License
Classifier: Natural Language :: Chinese (Simplified)
Classifier: Programming Language :: Python :: 3
Classifier: Programming Language :: Python :: 3.8
Classifier: Programming Language :: Python :: 3.9
Classifier: Programming Language :: Python :: 3.10
Classifier: Programming Language :: Python :: 3.11
Classifier: Programming Language :: Python :: 3.10
Classifier: Programming Language :: Python :: 3.11
Classifier: Programming Language :: Python :: 3.8
Classifier: Programming Language :: Python :: 3.9
Project-URL: Documentation, https://gitee.com/itxq/django-kelove-setting/blob/master/README.md
Project-URL: Repository, https://gitee.com/itxq/django-kelove-setting.git
